specforged/__init__.py
specforged/__main__.py
specforged/cli.py
specforged/prompts.py
specforged/resources.py
specforged/server.py
specforged/smithery_server.py
specforged/wizard.py
specforged/core/__init__.py
specforged/core/classifier.py
specforged/core/plan_generator.py
specforged/core/project_detector.py
specforged/core/spec_manager.py
specforged/models/__init__.py
specforged/models/core.py
specforged/templates/__init__.py
specforged/templates/rest_api.py
specforged/templates/web_app.py
specforged/tools/__init__.py
specforged/tools/classification.py
specforged/tools/filesystem.py
specforged/tools/planning.py
specforged/tools/specifications.py
specforged/tools/workflow.py
specforged-0.3.2.dist-info/METADATA
specforged-0.3.2.dist-info/WHEEL
specforged-0.3.2.dist-info/entry_points.txt
specforged-0.3.2.dist-info/RECORD
