Metadata-Version: 2.4
Name: specforged
Version: 0.3.2
Summary: Spec-driven development workflow with mode classification and EARS notation
Project-URL: Homepage, https://github.com/whit3rabbit/SpecForge
Project-URL: Documentation, https://github.com/whit3rabbit/SpecForge#readme
Project-URL: Repository, https://github.com/whit3rabbit/SpecForge.git
Project-URL: Issues, https://github.com/whit3rabbit/SpecForge/issues
Project-URL: PyPI, https://pypi.org/project/specforged/
Author: SpecForge Team
Maintainer: SpecForge Team
License: MIT
Keywords: ears,mcp,requirements,specifications,workflow
Classifier: Development Status :: 4 - Beta
Classifier: Environment :: Console
Classifier: Intended Audience :: Developers
Classifier: License :: OSI Approved :: MIT License
Classifier: Operating System :: OS Independent
Classifier: Programming Language :: Python :: 3
Classifier: Programming Language :: Python :: 3.10
Classifier: Programming Language :: Python :: 3.11
Classifier: Programming Language :: Python :: 3.12
Classifier: Topic :: Software Development :: Documentation
Classifier: Topic :: Software Development :: Libraries :: Python Modules
Classifier: Topic :: System :: Software Distribution
Requires-Python: >=3.10
Requires-Dist: aiofiles>=23.0.0
Requires-Dist: fastmcp>=0.3.0
Requires-Dist: mcp[cli]>=1.0.0
Requires-Dist: pydantic>=2.0.0
Requires-Dist: pytest-asyncio>=1.1.0
Requires-Dist: pytest>=8.4.1
Requires-Dist: questionary>=2.0.0
Requires-Dist: rich>=13.0.0
Requires-Dist: smithery>=0.1.23
Requires-Dist: starlette>=0.32.0
Requires-Dist: types-aiofiles>=23.0.0
Requires-Dist: uvicorn[standard]>=0.24.0
Provides-Extra: dev
Requires-Dist: black>=23.0.0; extra == 'dev'
Requires-Dist: flake8>=6.0.0; extra == 'dev'
Requires-Dist: mypy>=1.0.0; extra == 'dev'
Requires-Dist: pytest-asyncio>=0.21.0; extra == 'dev'
Requires-Dist: pytest>=7.0.0; extra == 'dev'
